odoo_restart/__init__.py
odoo_restart/restart.py
restart_odoo-0.1.0.dist-info/METADATA
restart_odoo-0.1.0.dist-info/WHEEL
restart_odoo-0.1.0.dist-info/entry_points.txt
restart_odoo-0.1.0.dist-info/top_level.txt
restart_odoo-0.1.0.dist-info/RECORD
