Metadata-Version: 2.1
Name: restart-odoo
Version: 0.1.0
Summary: Script to restart Odoo inside a Docker container
Home-page: https://github.com/mmasstou/ecic.git
Author: mohamed MASSTOUR
Author-email: masstour01@gmail.com
License: UNKNOWN
Platform: UNKNOWN
Requires-Dist: fabric
